README.txt
localexpansions.em
mkdocs.py
readme.txt
sample.em
setup.py
testlocal.cpp
testlocal.cpp.new
empywiz/em.py
empywiz/empywizcfg.py
empywiz/expandtemplate.py
empywiz/prjwiz.py
empywiz/wizdefaults.py
empywiz/wizprompters.py
empywiz.egg-info/PKG-INFO
empywiz.egg-info/SOURCES.txt
empywiz.egg-info/dependency_links.txt
empywiz.egg-info/entry_points.txt
empywiz.egg-info/top_level.txt
sampledir/empy_rename_files.em
sampledir/readme.txt
sampledir/sample1.txt.em
sampledir/sample2.txt.em
sampledir/vssver.scc
