Metadata-Version: 1.0
Name: empywiz
Version: 0.6
Summary: Wizard for EmPy templates
Home-page: http://opensvn.csie.org/vvprj/trunk/empywiz/
Author: Ville M. Vainio
Author-email: vivainio@gmail.com
License: UNKNOWN
Platform: UNKNOWN
